prowler/__init__.py
prowler_py-0.0.1.dist-info/LICENSE
prowler_py-0.0.1.dist-info/METADATA
prowler_py-0.0.1.dist-info/WHEEL
prowler_py-0.0.1.dist-info/entry_points.txt
prowler_py-0.0.1.dist-info/top_level.txt
prowler_py-0.0.1.dist-info/RECORD
