Metadata-Version: 2.1
Name: prowler-py
Version: 0.0.1
Summary: Prowler is a security tool to perform AWS security best practices assessments, audits, incident response, continuous monitoring, hardening and forensics readiness.
Home-page: https://github.com/nalansitan/prowler-py/
Author: nalansitan
Author-email: nalansitan@gmail.com
License: UNKNOWN
Project-URL: Bug Reports, https://github.com/nalansitan/prowler-py/issues
Project-URL: Source, https://github.com/nalansitan/prowler-py/
Platform: UNKNOWN
Classifier: Development Status :: 3 - Alpha
Classifier: Intended Audience :: Developers
Classifier: Topic :: Security
Classifier: License :: OSI Approved :: Apache Software License
Classifier: Programming Language :: Python :: 3
Classifier: Operating System :: OS Independent
Requires-Python: >=3.5
Requires-Dist: awscli
Requires-Dist: ansi2html
Requires-Dist: detect-secrets
